{
    "arkworks": {
        "label": "arkworks-rs",
        "version": "0.4 (rustc: 1.68.0-nightly) ",
        "url": "https://arkworks.rs/"
    },
    "blstrs": {
        "label": "blstrs",
        "version": "0.6.1 (rustc: 1.68.0-nightly)",
        "url": "https://github.com/filecoin-project/blstrs"
    },
    "curve25519_dalek": {
        "label": "curve25519-dalek-ng",
        "version": "4 (rustc: 1.68.0-nightly)",
        "url": "dalek.rs"
    },
    "zkcrypto": {
        "label": "zkcrypto",
        "version": "0.4 (rustc: 1.68.0-nightly)",
        "url": "https://github.com/zkcrypto/"
    },
    "gnark": {
        "label": "gnark",
        "version": "0.9.0 (branch: zkalc)",
        "url": "https://github.com/ConsenSys/gnark-crypto/"
    },
    "zcash": {
        "label": "zcash",
        "version": "0.5",
        "url": "https://github.com/zcash/pasta_curves"
    }
}
